<?xml version="1.0" encoding="UTF-8"?><record_update>
    <sys_ui_form_sections action="DELETE" form_id="369a4165dba600104ccedde7489619c9" sys_domain="global" table="x_58872_needit_needit" version="3">
        <sys_ui_form_section action="INSERT_OR_UPDATE">
            <position>0</position>
            <sys_created_by>admin</sys_created_by>
            <sys_created_on>2020-01-24 14:52:16</sys_created_on>
            <sys_domain>global</sys_domain>
            <sys_domain_path>/</sys_domain_path>
            <sys_id>f29a4165dba600104ccedde7489619cb</sys_id>
            <sys_mod_count>0</sys_mod_count>
            <sys_overrides/>
            <sys_ui_form display_value="x_58872_needit_needit" name="x_58872_needit_needit" sys_domain="global" view="3a9a4165dba600104ccedde7489619c4">369a4165dba600104ccedde7489619c9</sys_ui_form>
            <sys_ui_section caption="NULL" display_value="" name="x_58872_needit_needit" sys_domain="global" view="3a9a4165dba600104ccedde7489619c4">b29a4165dba600104ccedde7489619c7</sys_ui_section>
            <sys_updated_by>admin</sys_updated_by>
            <sys_updated_on>2020-01-24 14:52:16</sys_updated_on>
        </sys_ui_form_section>
        <sys_ui_form_section action="INSERT_OR_UPDATE">
            <position>1</position>
            <sys_created_by>admin</sys_created_by>
            <sys_created_on>2020-01-24 14:52:16</sys_created_on>
            <sys_domain>global</sys_domain>
            <sys_domain_path>/</sys_domain_path>
            <sys_id>be9a4165dba600104ccedde7489619cb</sys_id>
            <sys_mod_count>0</sys_mod_count>
            <sys_overrides/>
            <sys_ui_form display_value="x_58872_needit_needit" name="x_58872_needit_needit" sys_domain="global" view="3a9a4165dba600104ccedde7489619c4">369a4165dba600104ccedde7489619c9</sys_ui_form>
            <sys_ui_section caption="Log" display_value="Log" name="x_58872_needit_needit" sys_domain="global" view="3a9a4165dba600104ccedde7489619c4">7e9a4165dba600104ccedde7489619c7</sys_ui_section>
            <sys_updated_by>admin</sys_updated_by>
            <sys_updated_on>2020-01-24 14:52:16</sys_updated_on>
        </sys_ui_form_section>
        <sys_ui_form_section action="INSERT_OR_UPDATE">
            <position>2</position>
            <sys_created_by>admin</sys_created_by>
            <sys_created_on>2020-01-24 14:52:16</sys_created_on>
            <sys_domain>global</sys_domain>
            <sys_domain_path>/</sys_domain_path>
            <sys_id>769a4165dba600104ccedde7489619f4</sys_id>
            <sys_mod_count>0</sys_mod_count>
            <sys_overrides/>
            <sys_ui_form display_value="x_58872_needit_needit" name="x_58872_needit_needit" sys_domain="global" view="3a9a4165dba600104ccedde7489619c4">369a4165dba600104ccedde7489619c9</sys_ui_form>
            <sys_ui_section caption="Statistics" display_value="Statistics" name="x_58872_needit_needit" sys_domain="global" view="3a9a4165dba600104ccedde7489619c4">b69a4165dba600104ccedde7489619c8</sys_ui_section>
            <sys_updated_by>admin</sys_updated_by>
            <sys_updated_on>2020-01-24 14:52:16</sys_updated_on>
        </sys_ui_form_section>
        <sys_ui_form action="INSERT_OR_UPDATE">
            <name>x_58872_needit_needit</name>
            <roles/>
            <sys_class_name>sys_ui_form</sys_class_name>
            <sys_created_by>admin</sys_created_by>
            <sys_created_on>2020-01-24 14:52:16</sys_created_on>
            <sys_domain>global</sys_domain>
            <sys_domain_path>/</sys_domain_path>
            <sys_id>369a4165dba600104ccedde7489619c9</sys_id>
            <sys_mod_count>0</sys_mod_count>
            <sys_name>x_58872_needit_needit</sys_name>
            <sys_overrides/>
            <sys_package display_value="NeedIt" source="x_58872_needit">6ead8e780f603200cd674f8ce1050ed1</sys_package>
            <sys_policy/>
            <sys_scope display_value="NeedIt">6ead8e780f603200cd674f8ce1050ed1</sys_scope>
            <sys_update_name>sys_ui_form_sections_369a4165dba600104ccedde7489619c9</sys_update_name>
            <sys_updated_by>admin</sys_updated_by>
            <sys_updated_on>2020-01-24 14:52:16</sys_updated_on>
            <sys_user/>
            <view display_value="Default_view" name="Default_view">3a9a4165dba600104ccedde7489619c4</view>
            <view_name/>
        </sys_ui_form>
    </sys_ui_form_sections>
    <sys_update_version action="INSERT_OR_UPDATE">
        <action>DELETE</action>
        <application display_value="NeedIt">6ead8e780f603200cd674f8ce1050ed1</application>
        <file_path/>
        <instance_id>52b237c1dbc3d3c06578f22ebf96199c</instance_id>
        <instance_name>dev63078</instance_name>
        <name>sys_ui_form_sections_369a4165dba600104ccedde7489619c9</name>
        <payload><![CDATA[<?xml version="1.0" encoding="UTF-8"?><record_update><sys_ui_form_sections form_id="369a4165dba600104ccedde7489619c9" sys_domain="global" table="x_58872_needit_needit" version="3"><sys_ui_form_section action="INSERT_OR_UPDATE"><position>0</position><sys_created_by>admin</sys_created_by><sys_created_on>2020-01-24 14:52:16</sys_created_on><sys_domain>global</sys_domain><sys_domain_path>/</sys_domain_path><sys_id>f29a4165dba600104ccedde7489619cb</sys_id><sys_mod_count>0</sys_mod_count><sys_overrides/><sys_ui_form display_value="x_58872_needit_needit" name="x_58872_needit_needit" sys_domain="global" view="3a9a4165dba600104ccedde7489619c4">369a4165dba600104ccedde7489619c9</sys_ui_form><sys_ui_section caption="NULL" display_value="" name="x_58872_needit_needit" sys_domain="global" view="3a9a4165dba600104ccedde7489619c4">b29a4165dba600104ccedde7489619c7</sys_ui_section><sys_updated_by>admin</sys_updated_by><sys_updated_on>2020-01-24 14:52:16</sys_updated_on></sys_ui_form_section><sys_ui_form_section action="INSERT_OR_UPDATE"><position>1</position><sys_created_by>admin</sys_created_by><sys_created_on>2020-01-24 14:52:16</sys_created_on><sys_domain>global</sys_domain><sys_domain_path>/</sys_domain_path><sys_id>be9a4165dba600104ccedde7489619cb</sys_id><sys_mod_count>0</sys_mod_count><sys_overrides/><sys_ui_form display_value="x_58872_needit_needit" name="x_58872_needit_needit" sys_domain="global" view="3a9a4165dba600104ccedde7489619c4">369a4165dba600104ccedde7489619c9</sys_ui_form><sys_ui_section caption="Log" display_value="Log" name="x_58872_needit_needit" sys_domain="global" view="3a9a4165dba600104ccedde7489619c4">7e9a4165dba600104ccedde7489619c7</sys_ui_section><sys_updated_by>admin</sys_updated_by><sys_updated_on>2020-01-24 14:52:16</sys_updated_on></sys_ui_form_section><sys_ui_form_section action="INSERT_OR_UPDATE"><position>2</position><sys_created_by>admin</sys_created_by><sys_created_on>2020-01-24 14:52:16</sys_created_on><sys_domain>global</sys_domain><sys_domain_path>/</sys_domain_path><sys_id>769a4165dba600104ccedde7489619f4</sys_id><sys_mod_count>0</sys_mod_count><sys_overrides/><sys_ui_form display_value="x_58872_needit_needit" name="x_58872_needit_needit" sys_domain="global" view="3a9a4165dba600104ccedde7489619c4">369a4165dba600104ccedde7489619c9</sys_ui_form><sys_ui_section caption="Statistics" display_value="Statistics" name="x_58872_needit_needit" sys_domain="global" view="3a9a4165dba600104ccedde7489619c4">b69a4165dba600104ccedde7489619c8</sys_ui_section><sys_updated_by>admin</sys_updated_by><sys_updated_on>2020-01-24 14:52:16</sys_updated_on></sys_ui_form_section><sys_ui_form action="INSERT_OR_UPDATE"><name>x_58872_needit_needit</name><roles/><sys_class_name>sys_ui_form</sys_class_name><sys_created_by>admin</sys_created_by><sys_created_on>2020-01-24 14:52:16</sys_created_on><sys_domain>global</sys_domain><sys_domain_path>/</sys_domain_path><sys_id>369a4165dba600104ccedde7489619c9</sys_id><sys_mod_count>0</sys_mod_count><sys_name>x_58872_needit_needit</sys_name><sys_overrides/><sys_package display_value="NeedIt" source="x_58872_needit">6ead8e780f603200cd674f8ce1050ed1</sys_package><sys_policy/><sys_scope display_value="NeedIt">6ead8e780f603200cd674f8ce1050ed1</sys_scope><sys_update_name>sys_ui_form_sections_369a4165dba600104ccedde7489619c9</sys_update_name><sys_updated_by>admin</sys_updated_by><sys_updated_on>2020-01-24 14:52:16</sys_updated_on><sys_user/><view display_value="Default_view" name="Default_view">3a9a4165dba600104ccedde7489619c4</view><view_name/></sys_ui_form></sys_ui_form_sections></record_update>]]></payload>
        <payload_hash>2558642</payload_hash>
        <record_name>NeedIt</record_name>
        <reverted_from/>
        <source>1d710169db6600104ccedde7489619a1</source>
        <source_table>sys_update_set</source_table>
        <state>previous</state>
        <sys_created_by>admin</sys_created_by>
        <sys_created_on>2020-01-24 14:52:16</sys_created_on>
        <sys_id>329a4165dba600104ccedde7489619f6</sys_id>
        <sys_mod_count>0</sys_mod_count>
        <sys_recorded_at>16fd80a13ec0000001</sys_recorded_at>
        <sys_updated_by>admin</sys_updated_by>
        <sys_updated_on>2020-01-24 14:52:16</sys_updated_on>
        <type>Form Sections</type>
        <update_guid>ba9a41654aa60010bf5ec429a146edf5</update_guid>
        <update_guid_history>ba9a41654aa60010bf5ec429a146edf5:2558642,3a9a416560a600105ee6bb6adef884f2:1944179992,b29a416599a60010ab792bd6a9daf0ca:-1060443976</update_guid_history>
    </sys_update_version>
    <sys_metadata_delete action="INSERT_OR_UPDATE">
        <sys_audit_delete/>
        <sys_class_name>sys_metadata_delete</sys_class_name>
        <sys_created_by>admin</sys_created_by>
        <sys_created_on>2020-01-24 14:53:24</sys_created_on>
        <sys_db_object display_value="" name="sys_ui_form">sys_ui_form</sys_db_object>
        <sys_id>4b8248535304406099db99e1a84f3824</sys_id>
        <sys_metadata>369a4165dba600104ccedde7489619c9</sys_metadata>
        <sys_mod_count>0</sys_mod_count>
        <sys_name>x_58872_needit_needit</sys_name>
        <sys_package display_value="NeedIt" source="x_58872_needit">6ead8e780f603200cd674f8ce1050ed1</sys_package>
        <sys_parent display_value="NeedIt">45007fcd0fa83200cd674f8ce1050ebc</sys_parent>
        <sys_policy/>
        <sys_scope display_value="NeedIt">6ead8e780f603200cd674f8ce1050ed1</sys_scope>
        <sys_scope_delete display_value="">94872a8897db403e8ee69a431de2fca4</sys_scope_delete>
        <sys_update_name>sys_ui_form_sections_369a4165dba600104ccedde7489619c9</sys_update_name>
        <sys_update_version display_value="sys_ui_form_sections_369a4165dba600104ccedde7489619c9">329a4165dba600104ccedde7489619f6</sys_update_version>
        <sys_updated_by>admin</sys_updated_by>
        <sys_updated_on>2020-01-24 14:53:24</sys_updated_on>
    </sys_metadata_delete>
</record_update>
